{
  "$schema": "https://schema.management.azure.com/schemas/2015-01-01/deploymentTemplate.json#",
  "contentVersion": "1.0.0.0",
  "parameters": {
    "newStorageAccountNamePrefix": {
      "value": "s####"
    },

    "vmNamePrefix": {
      "value": "v####"
    },

    "domainName": {
      "value": "contoso.com"
    },

    "dnsPrefix": {
      "value": "v####"
    },
    "location": {
      "value": "local"
    },

    "adminUsername": {
      "value": "Administrator"
    },
    "adminPassword": {
      "value": "!!123abcA"
    }
  }
}
